[
  {
    "title": "（示範）自然・水的三態",
    "subject": "自然",
    "status": "進行中",
    "stages": [
      "起始評估",
      "課程教學"
    ],
    "date": "2026-09-07",
    "note": "示範列：驗收駕駛艙版面用，開學前可整列刪除。連結先暫指班網常用網站頁。",
    "links": {
      "material": "",
      "pretest": "",
      "site": "https://flyshan2010.github.io/class-website/links.html",
      "differentiated": "",
      "exam": "",
      "review": ""
    }
  },
  {
    "title": "國語4上 L01 美麗島",
    "subject": "國語",
    "status": "進行中",
    "stages": [],
    "date": "",
    "note": "楊喚〈美麗島〉詩歌。2026-07-19 開單元。第一段起始評估已產出六合一前測卷（待老師驗收）；驗收通過後再勾「已完成階段」並續跑後四段。",
    "links": {
      "material": "https://drive.google.com/file/d/1fR3JmnVW1eN2lmk2ccqF9ISNR6O-IRb8/view?usp=drivesdk",
      "pretest": "https://drive.google.com/drive/folders/14z1ESZTH8DP1mO-AUj4HJq2MPllDmmcC",
      "site": "",
      "differentiated": "",
      "exam": "",
      "review": ""
    }
  }
]
